README.rst
setup.py
sarita/__init__.py
sarita/main.py
sarita.egg-info/PKG-INFO
sarita.egg-info/SOURCES.txt
sarita.egg-info/dependency_links.txt
sarita.egg-info/not-zip-safe
sarita.egg-info/top_level.txt
sarita/check/__init__.py
sarita/check/check.py
sarita/config/__init__.py
sarita/config/config.py
sarita/edit/__init__.py
sarita/edit/edit.py
sarita/inputPara/__init__.py
sarita/inputPara/inputPara.py
sarita/md2html/__init__.py
sarita/md2html/md2html.py
sarita/relation/__init__.py
sarita/relation/relation.py
sarita/theme/__init__.py
sarita/theme/theme.py