Metadata-Version: 1.1
Name: sarita
Version: 1.0
Summary: create your site easily
Home-page: https://uestcman.github.io
Author: Mr.Lution
Author-email: mrlution@qq.com
License: GPL License
Keywords: sarita
Platform: Linux
Classifier: Programming Language :: Python :: 2.7
